README.rst
setup.cfg
setup.py
hedgeye_analysis/__init__.py
hedgeye_analysis/hedgeye_analysis_boilerplate.py
hedgeye_analysis/hedgeye_clinical_trials.py
hedgeye_analysis/hedgeye_pandas_patch.py
hedgeye_analysis/hedgeye_stock_analysis.py
hedgeye_analysis/introspection.py
hedgeye_analysis.egg-info/PKG-INFO
hedgeye_analysis.egg-info/SOURCES.txt
hedgeye_analysis.egg-info/dependency_links.txt
hedgeye_analysis.egg-info/not-zip-safe
hedgeye_analysis.egg-info/requires.txt
hedgeye_analysis.egg-info/top_level.txt
test/test_hedgeye_analysis_boilerplate.py