Metadata-Version: 1.1
Name: hedgeye-analysis
Version: 0.1.7
Summary: Python analysis tools used by Hedgeye
Home-page: https://github.com/hedgeyedev/hedgeye-python-analysis/hedgeye_analysis
Author: James Lavin
Author-email: jlavin@hedgeye.com
License: MIT
Platform: UNKNOWN
Classifier: License :: OSI Approved :: MIT License
Classifier: Programming Language :: Python :: 3.4
